wire_st_sdk/__init__.py
wire_st_sdk/iolink/__init__.py
wire_st_sdk/iolink/iolink_device.py
wire_st_sdk/iolink/iolink_master.py
wire_st_sdk/iolink/iolink_protocol.py
wire_st_sdk/iolink/iolink_sensor.py
wire_st_sdk/utils/__init__.py
wire_st_sdk/utils/python_utils.py
wire_st_sdk/utils/wire_st_exceptions.py
wire_st_sdk-1.2.2.dist-info/LICENSE
wire_st_sdk-1.2.2.dist-info/METADATA
wire_st_sdk-1.2.2.dist-info/WHEEL
wire_st_sdk-1.2.2.dist-info/top_level.txt
wire_st_sdk-1.2.2.dist-info/RECORD
